tydeploy/__init__.py
tydeploy/functions.py
tydeploy/thread_pool.py
tydeploy/tydeploy.py
tydeploy/targets/__init__.py
tydeploy/targets/cos.py
tydeploy/targets/fs.py
tydeploy/targets/ssh.py
tydeploy/targets/zip.py
tydeploy-2.0.0.dist-info/LICENSE
tydeploy-2.0.0.dist-info/METADATA
tydeploy-2.0.0.dist-info/WHEEL
tydeploy-2.0.0.dist-info/entry_points.txt
tydeploy-2.0.0.dist-info/top_level.txt
tydeploy-2.0.0.dist-info/zip-safe
tydeploy-2.0.0.dist-info/RECORD
