Metadata-Version: 2.1
Name: tydeploy
Version: 2.0.0
Summary: Tianyi's Deploy Tool
Home-page: https://github.com/baobao1270/tydeploy.git
Author: Joseph Chris
Author-email: joseph@josephcz.xyz
License: GPL-3.0-or-later
Keywords: deployer
Platform: UNKNOWN
Classifier: Development Status :: 4 - Beta
Classifier: Programming Language :: Python :: 3 :: Only
Classifier: License :: OSI Approved :: GNU General Public License v3 or later (GPLv3+)
Classifier: Operating System :: OS Independent
License-File: LICENSE
Requires-Dist: paramiko (~=2.10.1)
Requires-Dist: toml (~=0.10.2)
Requires-Dist: cos-python-sdk-v5 (~=1.9.14)
Requires-Dist: minio (~=7.1.5)
